cdk_cloudformation_paloaltonetworks_cloudngfw_rulestack/__init__.py
cdk_cloudformation_paloaltonetworks_cloudngfw_rulestack/py.typed
cdk_cloudformation_paloaltonetworks_cloudngfw_rulestack/_jsii/__init__.py
cdk_cloudformation_paloaltonetworks_cloudngfw_rulestack/_jsii/paloaltonetworks-cloudngfw-rulestack@2.0.2-alpha.7.jsii.tgz
cdk_cloudformation_paloaltonetworks_cloudngfw_rulestack-2.0.2a7.dist-info/LICENSE
cdk_cloudformation_paloaltonetworks_cloudngfw_rulestack-2.0.2a7.dist-info/METADATA
cdk_cloudformation_paloaltonetworks_cloudngfw_rulestack-2.0.2a7.dist-info/WHEEL
cdk_cloudformation_paloaltonetworks_cloudngfw_rulestack-2.0.2a7.dist-info/top_level.txt
cdk_cloudformation_paloaltonetworks_cloudngfw_rulestack-2.0.2a7.dist-info/RECORD
