Metadata-Version: 2.1
Name: cdk-cloudformation-paloaltonetworks-cloudngfw-rulestack
Version: 2.0.2a7
Summary: A rulestack defines the NGFW's advanced access control (APP-ID, URL Filtering) and threat prevention behavior.
Home-page: https://github.com/aws-cloudformation/aws-cloudformation-rpdk.git
Author: Amazon Web Services
License: Apache-2.0
Project-URL: Source, https://github.com/cdklabs/cdk-cloudformation.git
Classifier: Intended Audience :: Developers
Classifier: Operating System :: OS Independent
Classifier: Programming Language :: JavaScript
Classifier: Programming Language :: Python :: 3 :: Only
Classifier: Programming Language :: Python :: 3.8
Classifier: Programming Language :: Python :: 3.9
Classifier: Programming Language :: Python :: 3.10
Classifier: Programming Language :: Python :: 3.11
Classifier: Typing :: Typed
Classifier: License :: OSI Approved
Requires-Python: ~=3.8
License-File: LICENSE
Requires-Dist: aws-cdk-lib <3.0.0,>=2.134.0
Requires-Dist: constructs <11.0.0,>=10.3.0
Requires-Dist: jsii <2.0.0,>=1.96.0
Requires-Dist: publication >=0.0.3
Requires-Dist: typeguard ~=2.13.3
